graphframes/__init__.py
graphframes/graphframe.py
graphframes/tests.py
graphframes/examples/__init__.py
graphframes/examples/belief_propagation.py
graphframes/examples/graphs.py
graphframes/lib/__init__.py
graphframes/lib/aggregate_messages.py
graphframes/lib/pregel.py
graphframes_dev-0.7.0.dist-info/METADATA
graphframes_dev-0.7.0.dist-info/WHEEL
graphframes_dev-0.7.0.dist-info/top_level.txt
graphframes_dev-0.7.0.dist-info/RECORD
