Metadata-Version: 2.1
Name: graphframes-dev
Version: 0.7.0
Summary: UNKNOWN
Home-page: UNKNOWN
Author: UNKNOWN
Author-email: UNKNOWN
License: UNKNOWN
Platform: UNKNOWN
Requires-Dist: nose (==1.3.3)
Requires-Dist: numpy (>=1.7)
